subprocess_maximize/__init__.py
subprocess_maximize-0.9.3.dist-info/DESCRIPTION.rst
subprocess_maximize-0.9.3.dist-info/LICENSE.txt
subprocess_maximize-0.9.3.dist-info/METADATA
subprocess_maximize-0.9.3.dist-info/RECORD
subprocess_maximize-0.9.3.dist-info/WHEEL
subprocess_maximize-0.9.3.dist-info/metadata.json
subprocess_maximize-0.9.3.dist-info/top_level.txt
