Metadata-Version: 2.0
Name: subprocess-maximize
Version: 0.9.3
Summary: Popen with process-priority and window-state
Home-page: https://github.com/HenkHcks/subprocess_maximize
Author: Henk
Author-email: UNKNOWN
License: MIT
Keywords: Popen subprocess
Platform: UNKNOWN
Classifier: Development Status :: 4 - Beta
Classifier: Intended Audience :: Developers
Classifier: License :: OSI Approved :: MIT License
Classifier: Programming Language :: Python :: 2
Classifier: Programming Language :: Python :: 2.7
Classifier: Programming Language :: Python :: 3
Classifier: Programming Language :: Python :: 3.3
Classifier: Programming Language :: Python :: 3.4
Classifier: Programming Language :: Python :: 3.5
Classifier: Programming Language :: Python :: 3.6
